<annotation>
    <folder>train</folder>
    <filename>flower-313.jpg</filename>
    <size>
        <width>3024</width>
        <height>4032</height>
        <depth>3</depth>
    </size>
    <segmented>0</segmented>
    <object>
        <name>Flor-Cerrada</name>
        <pose>Unspecified</pose>
        <truncated>0</truncated>
        <occluded>0</occluded>
        <difficult>0</difficult>
        <bndbox>
            <xmin>798</xmin>
            <ymin>1670</ymin>
            <xmax>988</xmax>
            <ymax>1812</ymax>
        </bndbox>
    </object>
    <object>
        <name>Flor-Cerrada</name>
        <pose>Unspecified</pose>
        <truncated>0</truncated>
        <occluded>0</occluded>
        <difficult>0</difficult>
        <bndbox>
            <xmin>1082</xmin>
            <ymin>2290</ymin>
            <xmax>1230</xmax>
            <ymax>2404</ymax>
        </bndbox>
    </object>
    <object>
        <name>Flor-Cerrada</name>
        <pose>Unspecified</pose>
        <truncated>0</truncated>
        <occluded>0</occluded>
        <difficult>0</difficult>
        <bndbox>
            <xmin>1499</xmin>
            <ymin>2310</ymin>
            <xmax>1672</xmax>
            <ymax>2476</ymax>
        </bndbox>
    </object>
    <object>
        <name>Flor-Cerrada</name>
        <pose>Unspecified</pose>
        <truncated>0</truncated>
        <occluded>0</occluded>
        <difficult>0</difficult>
        <bndbox>
            <xmin>1293</xmin>
            <ymin>2082</ymin>
            <xmax>1545</xmax>
            <ymax>2294</ymax>
        </bndbox>
    </object>
    <object>
        <name>Flor-Cerrada</name>
        <pose>Unspecified</pose>
        <truncated>0</truncated>
        <occluded>0</occluded>
        <difficult>0</difficult>
        <bndbox>
            <xmin>1081</xmin>
            <ymin>1530</ymin>
            <xmax>1344</xmax>
            <ymax>1765</ymax>
        </bndbox>
    </object>
    <object>
        <name>Flor-Cerrada</name>
        <pose>Unspecified</pose>
        <truncated>0</truncated>
        <occluded>0</occluded>
        <difficult>0</difficult>
        <bndbox>
            <xmin>304</xmin>
            <ymin>1200</ymin>
            <xmax>495</xmax>
            <ymax>1313</ymax>
        </bndbox>
    </object>
    <object>
        <name>Flor-Cerrada</name>
        <pose>Unspecified</pose>
        <truncated>0</truncated>
        <occluded>0</occluded>
        <difficult>0</difficult>
        <bndbox>
            <xmin>1009</xmin>
            <ymin>1145</ymin>
            <xmax>1316</xmax>
            <ymax>1422</ymax>
        </bndbox>
    </object>
    <object>
        <name>Flor-Cerrada</name>
        <pose>Unspecified</pose>
        <truncated>0</truncated>
        <occluded>0</occluded>
        <difficult>0</difficult>
        <bndbox>
            <xmin>1290</xmin>
            <ymin>1429</ymin>
            <xmax>1687</xmax>
            <ymax>1735</ymax>
        </bndbox>
    </object>
</annotation>