<annotation>
    <folder>images</folder>
    <filename>flower-232copy.jpg</filename>
    <size>
        <width>3024</width>
        <height>4032</height>
        <depth>3</depth>
    </size>
    <segmented>0</segmented>
    <object>
        <name>Flor-Cerrada</name>
        <pose>Unspecified</pose>
        <truncated>0</truncated>
        <occluded>0</occluded>
        <difficult>0</difficult>
        <bndbox>
            <xmin>2124</xmin>
            <ymin>3329</ymin>
            <xmax>2304</xmax>
            <ymax>3487</ymax>
        </bndbox>
    </object>
    <object>
        <name>Flor-Cerrada</name>
        <pose>Unspecified</pose>
        <truncated>0</truncated>
        <occluded>0</occluded>
        <difficult>0</difficult>
        <bndbox>
            <xmin>2432</xmin>
            <ymin>3055</ymin>
            <xmax>2693</xmax>
            <ymax>3319</ymax>
        </bndbox>
    </object>
    <object>
        <name>Flor-Cerrada</name>
        <pose>Unspecified</pose>
        <truncated>0</truncated>
        <occluded>0</occluded>
        <difficult>0</difficult>
        <bndbox>
            <xmin>1766</xmin>
            <ymin>3012</ymin>
            <xmax>1983</xmax>
            <ymax>3211</ymax>
        </bndbox>
    </object>
    <object>
        <name>Flor-Cerrada</name>
        <pose>Unspecified</pose>
        <truncated>0</truncated>
        <occluded>0</occluded>
        <difficult>0</difficult>
        <bndbox>
            <xmin>2047</xmin>
            <ymin>2916</ymin>
            <xmax>2314</xmax>
            <ymax>3179</ymax>
        </bndbox>
    </object>
    <object>
        <name>Flor-Cerrada</name>
        <pose>Unspecified</pose>
        <truncated>0</truncated>
        <occluded>0</occluded>
        <difficult>0</difficult>
        <bndbox>
            <xmin>1959</xmin>
            <ymin>3433</ymin>
            <xmax>2197</xmax>
            <ymax>3750</ymax>
        </bndbox>
    </object>
    <object>
        <name>Flor-Cerrada</name>
        <pose>Unspecified</pose>
        <truncated>0</truncated>
        <occluded>0</occluded>
        <difficult>0</difficult>
        <bndbox>
            <xmin>881</xmin>
            <ymin>3631</ymin>
            <xmax>1306</xmax>
            <ymax>3969</ymax>
        </bndbox>
    </object>
    <object>
        <name>Flor-Cerrada</name>
        <pose>Unspecified</pose>
        <truncated>0</truncated>
        <occluded>0</occluded>
        <difficult>0</difficult>
        <bndbox>
            <xmin>960</xmin>
            <ymin>3110</ymin>
            <xmax>1275</xmax>
            <ymax>3443</ymax>
        </bndbox>
    </object>
    <object>
        <name>Flor-Cerrada</name>
        <pose>Unspecified</pose>
        <truncated>0</truncated>
        <occluded>0</occluded>
        <difficult>0</difficult>
        <bndbox>
            <xmin>136</xmin>
            <ymin>3188</ymin>
            <xmax>591</xmax>
            <ymax>3555</ymax>
        </bndbox>
    </object>
    <object>
        <name>Flor-Cerrada</name>
        <pose>Unspecified</pose>
        <truncated>0</truncated>
        <occluded>0</occluded>
        <difficult>0</difficult>
        <bndbox>
            <xmin>889</xmin>
            <ymin>2618</ymin>
            <xmax>1210</xmax>
            <ymax>2968</ymax>
        </bndbox>
    </object>
    <object>
        <name>Flor-Cerrada</name>
        <pose>Unspecified</pose>
        <truncated>0</truncated>
        <occluded>0</occluded>
        <difficult>0</difficult>
        <bndbox>
            <xmin>1459</xmin>
            <ymin>2710</ymin>
            <xmax>1704</xmax>
            <ymax>2943</ymax>
        </bndbox>
    </object>
    <object>
        <name>Flor-Cerrada</name>
        <pose>Unspecified</pose>
        <truncated>0</truncated>
        <occluded>0</occluded>
        <difficult>0</difficult>
        <bndbox>
            <xmin>1725</xmin>
            <ymin>2495</ymin>
            <xmax>2100</xmax>
            <ymax>2900</ymax>
        </bndbox>
    </object>
    <object>
        <name>Flor-Cerrada</name>
        <pose>Unspecified</pose>
        <truncated>0</truncated>
        <occluded>0</occluded>
        <difficult>0</difficult>
        <bndbox>
            <xmin>1856</xmin>
            <ymin>2145</ymin>
            <xmax>2112</xmax>
            <ymax>2444</ymax>
        </bndbox>
    </object>
    <object>
        <name>Flor-Cerrada</name>
        <pose>Unspecified</pose>
        <truncated>0</truncated>
        <occluded>0</occluded>
        <difficult>0</difficult>
        <bndbox>
            <xmin>963</xmin>
            <ymin>1976</ymin>
            <xmax>1229</xmax>
            <ymax>2190</ymax>
        </bndbox>
    </object>
    <object>
        <name>Flor-Cerrada</name>
        <pose>Unspecified</pose>
        <truncated>0</truncated>
        <occluded>0</occluded>
        <difficult>0</difficult>
        <bndbox>
            <xmin>771</xmin>
            <ymin>2217</ymin>
            <xmax>1207</xmax>
            <ymax>2604</ymax>
        </bndbox>
    </object>
    <object>
        <name>Flor-Cerrada</name>
        <pose>Unspecified</pose>
        <truncated>0</truncated>
        <occluded>0</occluded>
        <difficult>0</difficult>
        <bndbox>
            <xmin>2421</xmin>
            <ymin>1973</ymin>
            <xmax>2679</xmax>
            <ymax>2288</ymax>
        </bndbox>
    </object>
    <object>
        <name>Flor-Cerrada</name>
        <pose>Unspecified</pose>
        <truncated>0</truncated>
        <occluded>0</occluded>
        <difficult>0</difficult>
        <bndbox>
            <xmin>2634</xmin>
            <ymin>1393</ymin>
            <xmax>2933</xmax>
            <ymax>1709</ymax>
        </bndbox>
    </object>
    <object>
        <name>Flor-Cerrada</name>
        <pose>Unspecified</pose>
        <truncated>0</truncated>
        <occluded>0</occluded>
        <difficult>0</difficult>
        <bndbox>
            <xmin>2190</xmin>
            <ymin>1282</ymin>
            <xmax>2415</xmax>
            <ymax>1519</ymax>
        </bndbox>
    </object>
    <object>
        <name>Flor-Cerrada</name>
        <pose>Unspecified</pose>
        <truncated>0</truncated>
        <occluded>0</occluded>
        <difficult>0</difficult>
        <bndbox>
            <xmin>1984</xmin>
            <ymin>1587</ymin>
            <xmax>2208</xmax>
            <ymax>1841</ymax>
        </bndbox>
    </object>
    <object>
        <name>Flor-Cerrada</name>
        <pose>Unspecified</pose>
        <truncated>0</truncated>
        <occluded>0</occluded>
        <difficult>0</difficult>
        <bndbox>
            <xmin>1612</xmin>
            <ymin>1758</ymin>
            <xmax>1940</xmax>
            <ymax>2109</ymax>
        </bndbox>
    </object>
    <object>
        <name>Flor-Cerrada</name>
        <pose>Unspecified</pose>
        <truncated>0</truncated>
        <occluded>0</occluded>
        <difficult>0</difficult>
        <bndbox>
            <xmin>1067</xmin>
            <ymin>1415</ymin>
            <xmax>1458</xmax>
            <ymax>1803</ymax>
        </bndbox>
    </object>
    <object>
        <name>Hoja-Sana</name>
        <pose>Unspecified</pose>
        <truncated>0</truncated>
        <occluded>0</occluded>
        <difficult>0</difficult>
        <bndbox>
            <xmin>503</xmin>
            <ymin>1668</ymin>
            <xmax>1056</xmax>
            <ymax>1996</ymax>
        </bndbox>
    </object>
    <object>
        <name>Hoja-Sana</name>
        <pose>Unspecified</pose>
        <truncated>0</truncated>
        <occluded>0</occluded>
        <difficult>0</difficult>
        <bndbox>
            <xmin>210</xmin>
            <ymin>833</ymin>
            <xmax>874</xmax>
            <ymax>1640</ymax>
        </bndbox>
    </object>
    <object>
        <name>Hoja-Sana</name>
        <pose>Unspecified</pose>
        <truncated>0</truncated>
        <occluded>0</occluded>
        <difficult>0</difficult>
        <bndbox>
            <xmin>1247</xmin>
            <ymin>3198</ymin>
            <xmax>1720</xmax>
            <ymax>3727</ymax>
        </bndbox>
    </object>
    <object>
        <name>Hoja-Sana</name>
        <pose>Unspecified</pose>
        <truncated>0</truncated>
        <occluded>0</occluded>
        <difficult>0</difficult>
        <bndbox>
            <xmin>897</xmin>
            <ymin>79</ymin>
            <xmax>1994</xmax>
            <ymax>731</ymax>
        </bndbox>
    </object>
</annotation>