<annotation>
    <folder>images</folder>
    <filename>flower-305.jpg</filename>
    <size>
        <width>3024</width>
        <height>4032</height>
        <depth>3</depth>
    </size>
    <segmented>0</segmented>
    <object>
        <name>Flor-Cerrada</name>
        <pose>Unspecified</pose>
        <truncated>0</truncated>
        <occluded>0</occluded>
        <difficult>0</difficult>
        <bndbox>
            <xmin>1399</xmin>
            <ymin>2491</ymin>
            <xmax>2064</xmax>
            <ymax>2833</ymax>
        </bndbox>
    </object>
    <object>
        <name>Flor-Cerrada</name>
        <pose>Unspecified</pose>
        <truncated>0</truncated>
        <occluded>0</occluded>
        <difficult>0</difficult>
        <bndbox>
            <xmin>1208</xmin>
            <ymin>126</ymin>
            <xmax>1733</xmax>
            <ymax>675</ymax>
        </bndbox>
    </object>
    <object>
        <name>Flor-Cerrada</name>
        <pose>Unspecified</pose>
        <truncated>0</truncated>
        <occluded>0</occluded>
        <difficult>0</difficult>
        <bndbox>
            <xmin>2008</xmin>
            <ymin>1184</ymin>
            <xmax>2451</xmax>
            <ymax>1670</ymax>
        </bndbox>
    </object>
    <object>
        <name>Flor-Abierta</name>
        <pose>Unspecified</pose>
        <truncated>0</truncated>
        <occluded>0</occluded>
        <difficult>0</difficult>
        <bndbox>
            <xmin>1085</xmin>
            <ymin>567</ymin>
            <xmax>2064</xmax>
            <ymax>1545</ymax>
        </bndbox>
    </object>
    <object>
        <name>Flor-Abierta</name>
        <pose>Unspecified</pose>
        <truncated>0</truncated>
        <occluded>0</occluded>
        <difficult>0</difficult>
        <bndbox>
            <xmin>504</xmin>
            <ymin>1381</ymin>
            <xmax>1219</xmax>
            <ymax>2253</ymax>
        </bndbox>
    </object>
    <object>
        <name>Flor-Abierta</name>
        <pose>Unspecified</pose>
        <truncated>0</truncated>
        <occluded>0</occluded>
        <difficult>0</difficult>
        <bndbox>
            <xmin>957</xmin>
            <ymin>1526</ymin>
            <xmax>2026</xmax>
            <ymax>2635</ymax>
        </bndbox>
    </object>
    <object>
        <name>Flor-Abierta</name>
        <pose>Unspecified</pose>
        <truncated>0</truncated>
        <occluded>0</occluded>
        <difficult>0</difficult>
        <bndbox>
            <xmin>2012</xmin>
            <ymin>1645</ymin>
            <xmax>2834</xmax>
            <ymax>2620</ymax>
        </bndbox>
    </object>
</annotation>