<annotation>
    <folder>images</folder>
    <filename>flower-98copy3.jpg</filename>
    <size>
        <width>3024</width>
        <height>4032</height>
        <depth>3</depth>
    </size>
    <segmented>0</segmented>
    <object>
        <name>Hoja-Minador</name>
        <pose>Unspecified</pose>
        <truncated>0</truncated>
        <occluded>0</occluded>
        <difficult>0</difficult>
        <bndbox>
            <xmin>1914</xmin>
            <ymin>2142</ymin>
            <xmax>2285</xmax>
            <ymax>2626</ymax>
        </bndbox>
    </object>
    <object>
        <name>Hoja-Minador</name>
        <pose>Unspecified</pose>
        <truncated>0</truncated>
        <occluded>0</occluded>
        <difficult>0</difficult>
        <bndbox>
            <xmin>1027</xmin>
            <ymin>2977</ymin>
            <xmax>1341</xmax>
            <ymax>3292</ymax>
        </bndbox>
    </object>
    <object>
        <name>Hoja-Minador</name>
        <pose>Unspecified</pose>
        <truncated>0</truncated>
        <occluded>0</occluded>
        <difficult>0</difficult>
        <bndbox>
            <xmin>2179</xmin>
            <ymin>3197</ymin>
            <xmax>2571</xmax>
            <ymax>3633</ymax>
        </bndbox>
    </object>
</annotation>