<annotation>
    <folder>images</folder>
    <filename>flower-142.jpg</filename>
    <size>
        <width>4032</width>
        <height>3024</height>
        <depth>3</depth>
    </size>
    <segmented>0</segmented>
    <object>
        <name>Hoja-Quimico</name>
        <pose>Unspecified</pose>
        <truncated>0</truncated>
        <occluded>0</occluded>
        <difficult>0</difficult>
        <bndbox>
            <xmin>1250</xmin>
            <ymin>2592</ymin>
            <xmax>1558</xmax>
            <ymax>2933</ymax>
        </bndbox>
    </object>
    <object>
        <name>Hoja-Quimico</name>
        <pose>Unspecified</pose>
        <truncated>0</truncated>
        <occluded>0</occluded>
        <difficult>0</difficult>
        <bndbox>
            <xmin>882</xmin>
            <ymin>2266</ymin>
            <xmax>1227</xmax>
            <ymax>2568</ymax>
        </bndbox>
    </object>
    <object>
        <name>Hoja-Quimico</name>
        <pose>Unspecified</pose>
        <truncated>0</truncated>
        <occluded>0</occluded>
        <difficult>0</difficult>
        <bndbox>
            <xmin>1292</xmin>
            <ymin>101</ymin>
            <xmax>1500</xmax>
            <ymax>311</ymax>
        </bndbox>
    </object>
    <object>
        <name>Hoja-Quimico</name>
        <pose>Unspecified</pose>
        <truncated>0</truncated>
        <occluded>0</occluded>
        <difficult>0</difficult>
        <bndbox>
            <xmin>2165</xmin>
            <ymin>55</ymin>
            <xmax>2486</xmax>
            <ymax>491</ymax>
        </bndbox>
    </object>
    <object>
        <name>Hoja-Quimico</name>
        <pose>Unspecified</pose>
        <truncated>0</truncated>
        <occluded>0</occluded>
        <difficult>0</difficult>
        <bndbox>
            <xmin>3491</xmin>
            <ymin>613</ymin>
            <xmax>3921</xmax>
            <ymax>973</ymax>
        </bndbox>
    </object>
    <object>
        <name>Hoja-Quimico</name>
        <pose>Unspecified</pose>
        <truncated>0</truncated>
        <occluded>0</occluded>
        <difficult>0</difficult>
        <bndbox>
            <xmin>3467</xmin>
            <ymin>876</ymin>
            <xmax>3921</xmax>
            <ymax>1147</ymax>
        </bndbox>
    </object>
    <object>
        <name>Hoja-Quimico</name>
        <pose>Unspecified</pose>
        <truncated>0</truncated>
        <occluded>0</occluded>
        <difficult>0</difficult>
        <bndbox>
            <xmin>2589</xmin>
            <ymin>1128</ymin>
            <xmax>2927</xmax>
            <ymax>1522</ymax>
        </bndbox>
    </object>
    <object>
        <name>Hoja-Quimico</name>
        <pose>Unspecified</pose>
        <truncated>0</truncated>
        <occluded>0</occluded>
        <difficult>0</difficult>
        <bndbox>
            <xmin>2203</xmin>
            <ymin>1240</ymin>
            <xmax>2492</xmax>
            <ymax>1521</ymax>
        </bndbox>
    </object>
    <object>
        <name>Hoja-Sana</name>
        <pose>Unspecified</pose>
        <truncated>0</truncated>
        <occluded>0</occluded>
        <difficult>0</difficult>
        <bndbox>
            <xmin>2533</xmin>
            <ymin>1481</ymin>
            <xmax>2976</xmax>
            <ymax>1852</ymax>
        </bndbox>
    </object>
    <object>
        <name>Hoja-Quimico</name>
        <pose>Unspecified</pose>
        <truncated>0</truncated>
        <occluded>0</occluded>
        <difficult>0</difficult>
        <bndbox>
            <xmin>2979</xmin>
            <ymin>1468</ymin>
            <xmax>3478</xmax>
            <ymax>1929</ymax>
        </bndbox>
    </object>
    <object>
        <name>Hoja-Sana</name>
        <pose>Unspecified</pose>
        <truncated>0</truncated>
        <occluded>0</occluded>
        <difficult>0</difficult>
        <bndbox>
            <xmin>1929</xmin>
            <ymin>2263</ymin>
            <xmax>2293</xmax>
            <ymax>2555</ymax>
        </bndbox>
    </object>
    <object>
        <name>Hoja-Sana</name>
        <pose>Unspecified</pose>
        <truncated>0</truncated>
        <occluded>0</occluded>
        <difficult>0</difficult>
        <bndbox>
            <xmin>2445</xmin>
            <ymin>2068</ymin>
            <xmax>2797</xmax>
            <ymax>2392</ymax>
        </bndbox>
    </object>
    <object>
        <name>Hoja-Sana</name>
        <pose>Unspecified</pose>
        <truncated>0</truncated>
        <occluded>0</occluded>
        <difficult>0</difficult>
        <bndbox>
            <xmin>908</xmin>
            <ymin>1492</ymin>
            <xmax>1248</xmax>
            <ymax>1929</ymax>
        </bndbox>
    </object>
    <object>
        <name>Hoja-Sana</name>
        <pose>Unspecified</pose>
        <truncated>0</truncated>
        <occluded>0</occluded>
        <difficult>0</difficult>
        <bndbox>
            <xmin>420</xmin>
            <ymin>1602</ymin>
            <xmax>871</xmax>
            <ymax>1979</ymax>
        </bndbox>
    </object>
    <object>
        <name>Hoja-Sana</name>
        <pose>Unspecified</pose>
        <truncated>0</truncated>
        <occluded>0</occluded>
        <difficult>0</difficult>
        <bndbox>
            <xmin>1004</xmin>
            <ymin>1837</ymin>
            <xmax>1389</xmax>
            <ymax>2203</ymax>
        </bndbox>
    </object>
</annotation>